{
  "id": "true-lies",
  "platform": "gg",
  "category": "main_game",
  "titles": [
    {
      "text": "True Lies",
      "lang": "en",
      "script": "Latn",
      "region": "us",
      "form": "official",
      "source": "wikipedia_ja",
      "verified": false
    },
    {
      "text": "トゥルーライズ",
      "lang": "ja",
      "script": "Kana",
      "region": "jp",
      "form": "official",
      "source": "wikipedia_ja",
      "verified": true
    }
  ],
  "external_ids": {
    "wikidata": "Q110397"
  },
  "descriptions": [
    {
      "text": "US-amerikanischer Film (1994)",
      "lang": "de",
      "source": "wikidata"
    },
    {
      "text": "1994 film by James Cameron",
      "lang": "en",
      "source": "wikidata"
    },
    {
      "text": "película de 1994 dirigida por James Cameron",
      "lang": "es",
      "source": "wikidata"
    },
    {
      "text": "film de James Cameron, sorti en 1994",
      "lang": "fr",
      "source": "wikidata"
    },
    {
      "text": "film del 1994 diretto da James Cameron",
      "lang": "it",
      "source": "wikidata"
    },
    {
      "text": "ジェームズ・キャメロン監督の1994年のアメリカ映画",
      "lang": "ja",
      "source": "wikidata"
    },
    {
      "text": "filme de 1994 dirigido por James Cameron",
      "lang": "pt",
      "source": "wikidata"
    },
    {
      "text": "фильм Джеймса Кэмерона (1994)",
      "lang": "ru",
      "source": "wikidata"
    }
  ]
}
