{
  "id": "super-mario-64-land",
  "platform": "n64",
  "category": "main_game",
  "titles": [
    {
      "text": "Super Mario 64 Land",
      "lang": "en",
      "script": "Latn",
      "region": "us",
      "form": "official",
      "source": "igdb",
      "verified": false
    }
  ],
  "external_ids": {
    "igdb": 132609
  },
  "first_release_date": "2019-11-10",
  "descriptions": [
    {
      "text": "Super Mario 64 Land is ROM hack/mod for Super Mario 64 inspired by Super Mario 3D Land's gameplay and aesthetics, featuring moves and power-ups (like Cat Mario and Tanuki Mario) not found in the original game and new mechanics (such as a ranking system).",
      "lang": "en",
      "source": "igdb"
    }
  ]
}
