{
  "id": "bubsy-in-claws-encounters-of-the-furred-kind",
  "platform": "md",
  "category": "main_game",
  "titles": [
    {
      "text": "やまねこバブジーの大冒険",
      "lang": "ja",
      "script": "Jpan",
      "region": "jp",
      "form": "official",
      "source": "wikidata",
      "verified": true
    },
    {
      "text": "Bubsy in: Claws Encounters of the Furred Kind",
      "lang": "en",
      "script": "Latn",
      "region": "us",
      "form": "official",
      "source": "wikidata",
      "verified": false
    },
    {
      "text": "Bubsy in: Claws Encounters of the Furred Kind",
      "lang": "es",
      "script": "Latn",
      "region": "es",
      "form": "official",
      "source": "wikidata",
      "verified": false
    },
    {
      "text": "Bubsy",
      "lang": "fr",
      "script": "Latn",
      "region": "fr",
      "form": "official",
      "source": "wikidata",
      "verified": false
    },
    {
      "text": "Bubsy in Claws Encounters of the Furred Kind",
      "lang": "de",
      "script": "Latn",
      "region": "de",
      "form": "official",
      "source": "wikidata",
      "verified": false
    },
    {
      "text": "Bubsy in Claws Encounters of the Furred Kind",
      "lang": "it",
      "script": "Latn",
      "region": "it",
      "form": "official",
      "source": "wikidata",
      "verified": false
    },
    {
      "text": "Yamaneko Bubsy no Daibouken",
      "lang": "en",
      "script": "Latn",
      "form": "romaji_transliteration",
      "source": "igdb",
      "verified": true
    }
  ],
  "first_release_date": "1993-01-01",
  "external_ids": {
    "wikidata": "Q12170990",
    "mobygames": 7145,
    "igdb": 7804
  },
  "roms": [
    {
      "name": "Bubsy in - Claws Encounters of the Furred Kind (USA, Europe)",
      "source": "no_intro",
      "region": "us",
      "serial": "T-119026-00",
      "size": 2097152,
      "crc32": "3e30d365",
      "md5": "a603f331d2d8700543a67c60342e38f7",
      "sha1": "719140754763e5062947ef9e76ee748cfad38202"
    }
  ],
  "media": [
    {
      "kind": "boxart",
      "url": "https://raw.githubusercontent.com/libretro-thumbnails/Sega_-_Mega_Drive_-_Genesis/master/Named_Boxarts/Bubsy%20in%20-%20Claws%20Encounters%20of%20the%20Furred%20Kind%20%28USA%2C%20Europe%29.png",
      "source": "libretro_thumbnails",
      "region": "us"
    },
    {
      "kind": "titlescreen",
      "url": "https://raw.githubusercontent.com/libretro-thumbnails/Sega_-_Mega_Drive_-_Genesis/master/Named_Titles/Bubsy%20in%20-%20Claws%20Encounters%20of%20the%20Furred%20Kind%20%28USA%2C%20Europe%29.png",
      "source": "libretro_thumbnails",
      "region": "us"
    },
    {
      "kind": "screenshot",
      "url": "https://raw.githubusercontent.com/libretro-thumbnails/Sega_-_Mega_Drive_-_Genesis/master/Named_Snaps/Bubsy%20in%20-%20Claws%20Encounters%20of%20the%20Furred%20Kind%20%28USA%2C%20Europe%29.png",
      "source": "libretro_thumbnails",
      "region": "us"
    }
  ]
}
