{
  "id": "nfl-prime-time-98",
  "platform": "md",
  "category": "main_game",
  "titles": [
    {
      "text": "NFL Prime Time '98",
      "lang": "en",
      "script": "Latn",
      "region": "us",
      "form": "official",
      "source": "wikidata",
      "verified": false
    },
    {
      "text": "NFL Prime Time '98",
      "lang": "fr",
      "script": "Latn",
      "region": "fr",
      "form": "official",
      "source": "wikidata",
      "verified": false
    },
    {
      "text": "NFL 98",
      "lang": "de",
      "script": "Latn",
      "region": "de",
      "form": "official",
      "source": "wikidata",
      "verified": false
    }
  ],
  "first_release_date": "1997-05-14",
  "external_ids": {
    "wikidata": "Q6953737",
    "mobygames": 46915
  }
}
