{
  "id": "team-usa-basketball",
  "platform": "md",
  "category": "main_game",
  "titles": [
    {
      "text": "ドリームチームUSA",
      "lang": "ja",
      "script": "Kana",
      "region": "jp",
      "form": "official",
      "source": "wikidata",
      "verified": false
    },
    {
      "text": "Team USA Basketball",
      "lang": "en",
      "script": "Latn",
      "region": "us",
      "form": "official",
      "source": "wikidata",
      "verified": false
    },
    {
      "text": "Team USA Basketball",
      "lang": "fr",
      "script": "Latn",
      "region": "fr",
      "form": "official",
      "source": "wikidata",
      "verified": false
    },
    {
      "text": "Team USA Basketball",
      "lang": "it",
      "script": "Latn",
      "region": "it",
      "form": "official",
      "source": "wikidata",
      "verified": false
    }
  ],
  "first_release_date": "1992-01-01",
  "external_ids": {
    "wikidata": "Q3516725",
    "mobygames": 13284,
    "igdb": 46260
  },
  "roms": [
    {
      "name": "Team USA Basketball (USA, Europe)",
      "source": "no_intro",
      "region": "us",
      "serial": "T-50376-00",
      "size": 1048576,
      "crc32": "a0caf97e",
      "md5": "e76e5159921402923bf4b16462e9c261",
      "sha1": "8d8d833dfc88663408bd7cf9fb821608ad2bef3d",
      "sha256": "962d674c654a1313c40ffc2abaab2e1f25f3f6cebf6a17c8ee4898f5d04f0861"
    }
  ],
  "media": [
    {
      "kind": "boxart",
      "url": "https://raw.githubusercontent.com/libretro-thumbnails/Sega_-_Mega_Drive_-_Genesis/master/Named_Boxarts/Team%20USA%20Basketball%20%28USA%2C%20Europe%29.png",
      "source": "libretro_thumbnails",
      "region": "us"
    },
    {
      "kind": "titlescreen",
      "url": "https://raw.githubusercontent.com/libretro-thumbnails/Sega_-_Mega_Drive_-_Genesis/master/Named_Titles/Team%20USA%20Basketball%20%28USA%2C%20Europe%29.png",
      "source": "libretro_thumbnails",
      "region": "us"
    },
    {
      "kind": "screenshot",
      "url": "https://raw.githubusercontent.com/libretro-thumbnails/Sega_-_Mega_Drive_-_Genesis/master/Named_Snaps/Team%20USA%20Basketball%20%28USA%2C%20Europe%29.png",
      "source": "libretro_thumbnails",
      "region": "us"
    },
    {
      "kind": "boxart",
      "url": "https://raw.githubusercontent.com/libretro-thumbnails/Sega_-_Mega_Drive_-_Genesis/master/Named_Boxarts/Team%20USA%20Basketball%20%28USA%29.png",
      "source": "libretro_thumbnails"
    }
  ],
  "descriptions": [
    {
      "text": "videojuego de 1992",
      "lang": "es",
      "source": "wikidata"
    },
    {
      "text": "jeu vidéo de 1992",
      "lang": "fr",
      "source": "wikidata"
    },
    {
      "text": "videogioco del 1992",
      "lang": "it",
      "source": "wikidata"
    },
    {
      "text": "videojogo de 1992",
      "lang": "pt",
      "source": "wikidata"
    },
    {
      "text": "компьютерная игра 1992 года",
      "lang": "ru",
      "source": "wikidata"
    },
    {
      "text": "Computerspiel aus dem Jahr 1992",
      "lang": "de",
      "source": "wikidata"
    },
    {
      "text": "1992 video game",
      "lang": "en",
      "source": "wikidata"
    },
    {
      "text": "Team USA Basketball is a 1992 sports video game released on the Sega Genesis. The game is a spinoff following the success of the Bulls vs Lakers video game as well as the popularity explosion of the 1992 United States men's Olympic basketball team, also known as the \"Dream Team\". It is the third game in the NBA Playoffs series of games.\nA three-card set was bundled with each copy of the game. Put together, the cards showed the entire roster against a sky background with the words, \"BARCELONA '92\" in red and white.",
      "lang": "en",
      "source": "wikipedia_en"
    },
    {
      "text": "Team USA Basketball est un jeu vidéo de basket-ball sorti en 1992 sur Mega Drive. Le jeu a été développé et édité par Electronic Arts. Le jeu est basé sur les Jeux olympiques de Barcelone où avait joué la Dream Team américaine.",
      "lang": "fr",
      "source": "wikipedia_fr"
    },
    {
      "text": "Team USA Basketball è un videogioco sportivo del 1992 sviluppato da Electronic Arts per Sega Mega Drive. Distribuito in Giappone come Dream Team USA (ドリームチームＵＳＡ?), il gioco è incentrato sul Dream Team che ha partecipato al torneo di pallacanestro ai Giochi della XXV Olimpiade.",
      "lang": "it",
      "source": "wikipedia_it"
    },
    {
      "text": "『チームUSAバスケットボール』は、セガジェネシスで発売された1992年のスポーツビデオゲームです。このゲームは、『ブルズ対レイカーズ』の成功、そして「ドリームチーム」としても知られる1992年アメリカ男子オリンピックバスケットボールチームの爆発的な人気に触発されたスピンオフ作品です。NBAプレーオフシリーズにおける3作目の作品にあたります。\n\nゲームの各コピーには、3枚組のカードが同梱されていました。これらを合わせると、空を背景に全選手が描かれ、赤と白の文字で「BARCELONA '92」と記されていました。",
      "lang": "ja",
      "source": "ai_local_gemma4",
      "base_lang": "en"
    }
  ]
}
