{
  "id": "sydney-hunter-and-the-caverns-of-death",
  "platform": "sfc",
  "category": "main_game",
  "titles": [
    {
      "text": "Sydney Hunter and the Caverns of Death",
      "lang": "en",
      "script": "Latn",
      "region": "us",
      "form": "official",
      "source": "igdb",
      "verified": false
    }
  ],
  "external_ids": {
    "igdb": 61219
  },
  "first_release_date": "2012-08-12",
  "descriptions": [
    {
      "text": "Sydney Hunter and the Caverns of Death is a retro platformer that started as a Flash game before being ported to various older and modern platforms.",
      "lang": "en",
      "source": "igdb"
    }
  ]
}
