{
  "id": "oeka-kids-anpanman-no-hiragana-daisuki",
  "platform": "fc",
  "category": "main_game",
  "titles": [
    {
      "text": "Oeka Kids - Anpanman no Hiragana Daisuki",
      "lang": "en",
      "script": "Latn",
      "form": "official",
      "source": "no_intro",
      "verified": false,
      "region": "jp"
    },
    {
      "text": "おえかキッズ アンパンマンのひらがなだいすき",
      "lang": "ja",
      "script": "Jpan",
      "region": "jp",
      "form": "official",
      "source": "romu",
      "verified": true
    }
  ],
  "roms": [
    {
      "name": "Oeka Kids - Anpanman no Hiragana Daisuki (Japan)",
      "source": "no_intro",
      "region": "jp",
      "size": 131088,
      "crc32": "f94f5726",
      "md5": "a3bce9f8bec7acc54f065ef7df2b66d0",
      "sha1": "debefc777d49f099e3ccc7b6191ae665d1217abe",
      "sha256": "e8e5e63f592b7b59eda7d4bfe322a3a9860a3be97a0dfbcfeba728221fe69e21"
    }
  ],
  "external_ids": {
    "igdb": 48800
  },
  "descriptions": [
    {
      "text": "このゲームは子供向けの人気アニメシリーズに基づいています。主人公のアンパンマンは、パン屋のジャムおじさんの息子です。彼の頭は完全にパンとあんこでできています。彼は飢えている生き物たちを助け、彼の頭の一部を食べさせ、悪のバイキンマンとその手下たちと戦います。\n\nこのゲームには5つのミニゲームが含まれており、その中には教育的な目的を持つものもあります。ゲームは特別なマウスのようなデバイスで完全に操作されます。このデバイスはゲームと一緒に発送されます。ミニゲームは以下の通りです：\n\n1. アンパンマンが空から落とすリンゴを小さなフィールドを走り回ってキャッチします。\n\n2. パズルのピースを組み合わせてアニメのキャラクターの画像を作成します。\n\n3. アンパンマンの助けを借りて日本の音節（ひらがな）を書く練習をします。\n\n4. 似たような絵の違いを見つけます。\n\n5. ボードの空いているスペースをクリックしてキャラクターの顔を明らかにします。敵の顔を明らかにすると失敗になります（マインスイーパーに似た概念です）。",
      "lang": "ja",
      "source": "romu"
    },
    {
      "text": "An educational game to teach children Hiragana.\n\nOeka Kids: Anpanman no Hiragana Daisuki is a Miscellaneous game, developed by TOSE and published by Bandai, which was released in Japan in 1991.",
      "lang": "en",
      "source": "igdb"
    }
  ],
  "media": [
    {
      "kind": "boxart",
      "url": "https://raw.githubusercontent.com/libretro-thumbnails/Nintendo_-_Nintendo_Entertainment_System/master/Named_Boxarts/Oeka%20Kids%20-%20Anpanman%20no%20Hiragana%20Daisuki%20%28Japan%29.png",
      "source": "libretro_thumbnails",
      "region": "jp"
    },
    {
      "kind": "titlescreen",
      "url": "https://raw.githubusercontent.com/libretro-thumbnails/Nintendo_-_Nintendo_Entertainment_System/master/Named_Titles/Oeka%20Kids%20-%20Anpanman%20no%20Hiragana%20Daisuki%20%28Japan%29.png",
      "source": "libretro_thumbnails",
      "region": "jp"
    },
    {
      "kind": "screenshot",
      "url": "https://raw.githubusercontent.com/libretro-thumbnails/Nintendo_-_Nintendo_Entertainment_System/master/Named_Snaps/Oeka%20Kids%20-%20Anpanman%20no%20Hiragana%20Daisuki%20%28Japan%29.png",
      "source": "libretro_thumbnails",
      "region": "jp"
    }
  ]
}
