{
  "id": "side-pocket",
  "platform": "fc",
  "category": "main_game",
  "titles": [
    {
      "text": "サイドポケット",
      "lang": "ja",
      "script": "Kana",
      "region": "jp",
      "form": "official",
      "source": "wikidata",
      "verified": true
    },
    {
      "text": "Side Pocket",
      "lang": "en",
      "script": "Latn",
      "region": "us",
      "form": "official",
      "source": "wikidata",
      "verified": false
    },
    {
      "text": "Side Pocket",
      "lang": "fr",
      "script": "Latn",
      "region": "fr",
      "form": "official",
      "source": "wikidata",
      "verified": false
    },
    {
      "text": "Side Pocket",
      "lang": "de",
      "script": "Latn",
      "region": "de",
      "form": "official",
      "source": "wikidata",
      "verified": false
    },
    {
      "text": "Side Pocket",
      "lang": "it",
      "script": "Latn",
      "region": "it",
      "form": "official",
      "source": "wikidata",
      "verified": false
    }
  ],
  "first_release_date": "1986-06-01",
  "external_ids": {
    "wikidata": "Q2034580",
    "mobygames": 17479,
    "igdb": 288104
  },
  "roms": [
    {
      "name": "Side Pocket (Europe)",
      "source": "no_intro",
      "region": "eu",
      "size": 131088,
      "crc32": "97b3b3c0",
      "md5": "500bd0db5d03601eec6d28fc6c0f0197",
      "sha1": "c4988a41b9c87e0e698e0b7decbaf3de5f30499b",
      "sha256": "06e17801d41f6f452001d97c61c519fbfbf533f080b7bdef3f4e7d40800b90e2"
    },
    {
      "name": "Side Pocket (Japan)",
      "source": "no_intro",
      "region": "jp",
      "size": 163856,
      "crc32": "bd52d4d0",
      "md5": "b25348ddf62d5b51c3694eec5276c338",
      "sha1": "8606ecee84618bae70041672dded7f605860f996",
      "sha256": "5954bbe3b716f6a36d3e0279fdb0959af69b214efe37d8367ad676ce9e170f1c"
    },
    {
      "name": "Side Pocket (USA)",
      "source": "no_intro",
      "region": "us",
      "size": 131088,
      "crc32": "887d10da",
      "md5": "8a418ee0376dca3cff1eadf33d7671f3",
      "sha1": "8e76b30b7ba9d15203b49b77ba2ea97995441a57",
      "sha256": "1238f26c688362494a4411db6dd7d1f77efa67fd0c9cda46422795028e157445"
    },
    {
      "name": "Side Pocket (Asia) (En) (Pirate)",
      "source": "no_intro",
      "size": 131088,
      "crc32": "1376a389",
      "md5": "40975ff0ebc6ba5d5dc9312de92f15a6",
      "sha1": "dd230fbce5edd08e06bed3271a6f48bccc9351eb",
      "sha256": "b399d114efbe71b0df688b796aa8bcd01f314dd60ad8b93041106d9d468d6d2c"
    },
    {
      "name": "Side Pocket (Russia) (Pirate)",
      "source": "no_intro",
      "size": 131088,
      "crc32": "753805ba",
      "md5": "e7865d0f7452a6727d8943effc88990d",
      "sha1": "828df06695769820eea258373a2d8b9e69f7775c",
      "sha256": "be1e36587ee4c13d09947436b03a362bd206eb1098cdc663d4e2a1a271fe5884"
    }
  ],
  "media": [
    {
      "kind": "boxart",
      "url": "https://raw.githubusercontent.com/libretro-thumbnails/Nintendo_-_Nintendo_Entertainment_System/master/Named_Boxarts/Side%20Pocket%20%28Europe%29.png",
      "source": "libretro_thumbnails",
      "region": "eu"
    },
    {
      "kind": "titlescreen",
      "url": "https://raw.githubusercontent.com/libretro-thumbnails/Nintendo_-_Nintendo_Entertainment_System/master/Named_Titles/Side%20Pocket%20%28Europe%29.png",
      "source": "libretro_thumbnails",
      "region": "eu"
    },
    {
      "kind": "screenshot",
      "url": "https://raw.githubusercontent.com/libretro-thumbnails/Nintendo_-_Nintendo_Entertainment_System/master/Named_Snaps/Side%20Pocket%20%28Europe%29.png",
      "source": "libretro_thumbnails",
      "region": "eu"
    },
    {
      "kind": "boxart",
      "url": "https://raw.githubusercontent.com/libretro-thumbnails/Nintendo_-_Nintendo_Entertainment_System/master/Named_Boxarts/Side%20Pocket%20%28Japan%29.png",
      "source": "libretro_thumbnails",
      "region": "jp"
    },
    {
      "kind": "titlescreen",
      "url": "https://raw.githubusercontent.com/libretro-thumbnails/Nintendo_-_Nintendo_Entertainment_System/master/Named_Titles/Side%20Pocket%20%28Japan%29.png",
      "source": "libretro_thumbnails",
      "region": "jp"
    },
    {
      "kind": "screenshot",
      "url": "https://raw.githubusercontent.com/libretro-thumbnails/Nintendo_-_Nintendo_Entertainment_System/master/Named_Snaps/Side%20Pocket%20%28Japan%29.png",
      "source": "libretro_thumbnails",
      "region": "jp"
    },
    {
      "kind": "boxart",
      "url": "https://raw.githubusercontent.com/libretro-thumbnails/Nintendo_-_Nintendo_Entertainment_System/master/Named_Boxarts/Side%20Pocket%20%28USA%29.png",
      "source": "libretro_thumbnails",
      "region": "us"
    },
    {
      "kind": "titlescreen",
      "url": "https://raw.githubusercontent.com/libretro-thumbnails/Nintendo_-_Nintendo_Entertainment_System/master/Named_Titles/Side%20Pocket%20%28USA%29.png",
      "source": "libretro_thumbnails",
      "region": "us"
    },
    {
      "kind": "screenshot",
      "url": "https://raw.githubusercontent.com/libretro-thumbnails/Nintendo_-_Nintendo_Entertainment_System/master/Named_Snaps/Side%20Pocket%20%28USA%29.png",
      "source": "libretro_thumbnails",
      "region": "us"
    },
    {
      "kind": "titlescreen",
      "url": "https://raw.githubusercontent.com/libretro-thumbnails/Nintendo_-_Nintendo_Entertainment_System/master/Named_Titles/Side%20Pocket%20%28Russia%29%20%28Pirate%29.png",
      "source": "libretro_thumbnails"
    },
    {
      "kind": "screenshot",
      "url": "https://raw.githubusercontent.com/libretro-thumbnails/Nintendo_-_Nintendo_Entertainment_System/master/Named_Snaps/Side%20Pocket%20%28Russia%29%20%28Pirate%29.png",
      "source": "libretro_thumbnails"
    }
  ]
}
