{
  "id": "island-xtreme-stunts",
  "platform": "gba",
  "category": "main_game",
  "titles": [
    {
      "text": "アイランドエクストリームスタント",
      "lang": "ja",
      "script": "Kana",
      "region": "jp",
      "form": "official",
      "source": "wikidata",
      "verified": false
    },
    {
      "text": "Island Xtreme Stunts",
      "lang": "en",
      "script": "Latn",
      "region": "us",
      "form": "official",
      "source": "wikidata",
      "verified": false
    },
    {
      "text": "Island Xtreme Stunts",
      "lang": "fr",
      "script": "Latn",
      "region": "fr",
      "form": "official",
      "source": "wikidata",
      "verified": false
    }
  ],
  "first_release_date": "2002-11-15",
  "external_ids": {
    "wikidata": "Q110253213",
    "igdb": 300709
  },
  "roms": [
    {
      "name": "Island Xtreme Stunts (USA, Europe) (En,Fr,De,Es,It,Nl,Sv,Da)",
      "source": "no_intro",
      "region": "us",
      "serial": "AXTE",
      "size": 4194304,
      "crc32": "3beb5446",
      "md5": "081eb069af9e5cdc0cb7515a7249ba52",
      "sha1": "4eec876994bdea873188fe10033c48c924d129ec",
      "sha256": "194cb107f1355292c86b56b76c937fd853ba8eb81cc2637aa56c3a2e47bcf4d1"
    }
  ],
  "media": [
    {
      "kind": "boxart",
      "url": "https://raw.githubusercontent.com/libretro-thumbnails/Nintendo_-_Game_Boy_Advance/master/Named_Boxarts/Island%20Xtreme%20Stunts%20%28USA%2C%20Europe%29%20%28En%2CFr%2CDe%2CEs%2CIt%2CNl%2CSv%2CDa%29.png",
      "source": "libretro_thumbnails",
      "region": "us"
    },
    {
      "kind": "titlescreen",
      "url": "https://raw.githubusercontent.com/libretro-thumbnails/Nintendo_-_Game_Boy_Advance/master/Named_Titles/Island%20Xtreme%20Stunts%20%28USA%2C%20Europe%29%20%28En%2CFr%2CDe%2CEs%2CIt%2CNl%2CSv%2CDa%29.png",
      "source": "libretro_thumbnails",
      "region": "us"
    },
    {
      "kind": "screenshot",
      "url": "https://raw.githubusercontent.com/libretro-thumbnails/Nintendo_-_Game_Boy_Advance/master/Named_Snaps/Island%20Xtreme%20Stunts%20%28USA%2C%20Europe%29%20%28En%2CFr%2CDe%2CEs%2CIt%2CNl%2CSv%2CDa%29.png",
      "source": "libretro_thumbnails",
      "region": "us"
    }
  ],
  "descriptions": [
    {
      "text": "Island Xtreme Stunts is a mixture of different genres in a single game. The player goes through a level-select on the overworld to choose each mission. You ride a skateboard, drive, fly and more, while sometimes taking on the evil Brickster. The player is cast as Pepper Roni, a lead stuntman in a big movie production set on LEGO Island.",
      "lang": "en",
      "source": "igdb"
    },
    {
      "text": "2002 video game for Game Boy Advance",
      "lang": "en",
      "source": "wikidata"
    },
    {
      "text": "jeu vidéo de 2002 sur Game Boy Advance",
      "lang": "fr",
      "source": "wikidata"
    },
    {
      "text": "Island Xtreme Stunts is an action-adventure video game, and the sequel to Lego Island 2: The Brickster's Revenge, making it the third and final game in the Lego Island series, despite dropping the original Lego Island title and logo from the name. Like Lego Island 2, the game was developed by Silicon Dreams Studio. It was co-published by Electronic Arts and Lego Interactive, and was released in 2002, for the PlayStation 2 and Microsoft Windows, with a spin-off also released for Game Boy Advance.",
      "lang": "en",
      "source": "wikipedia_en"
    }
  ]
}
