{
  "id": "princess-blue-hime-kishi-monogatari",
  "platform": "gba",
  "category": "main_game",
  "titles": [
    {
      "text": "Princess Blue: Hime Kishi Monogatari",
      "lang": "en",
      "script": "Latn",
      "region": "us",
      "form": "official",
      "source": "igdb",
      "verified": false
    }
  ],
  "external_ids": {
    "igdb": 49628
  },
  "first_release_date": "2002-09-29",
  "descriptions": [
    {
      "text": "Princess Blue: Hime Kishi Monogatari is an Action game, published by Tonkin House, which was released in Japan in 2002.",
      "lang": "en",
      "source": "igdb"
    }
  ]
}
