{
  "id": "a-neko-story",
  "platform": "nds",
  "category": "main_game",
  "titles": [
    {
      "text": "A Neko Story",
      "lang": "en",
      "script": "Latn",
      "region": "us",
      "form": "official",
      "source": "igdb",
      "verified": false
    }
  ],
  "external_ids": {
    "igdb": 221012
  },
  "first_release_date": "2008-12-31",
  "descriptions": [
    {
      "text": "A Neko Story is a visual novel game for the Nintendo DS.",
      "lang": "en",
      "source": "igdb"
    }
  ]
}
