{
  "id": "mega-man-zx",
  "platform": "nds",
  "category": "main_game",
  "titles": [
    {
      "text": "ロックマンゼクス",
      "lang": "ja",
      "script": "Kana",
      "region": "jp",
      "form": "official",
      "source": "wikidata",
      "verified": false
    },
    {
      "text": "Mega Man ZX",
      "lang": "en",
      "script": "Latn",
      "region": "us",
      "form": "official",
      "source": "wikidata",
      "verified": false
    },
    {
      "text": "록맨 ZX",
      "lang": "ko",
      "script": "Hang",
      "region": "kr",
      "form": "official",
      "source": "wikidata",
      "verified": false
    },
    {
      "text": "洛克人ZX",
      "lang": "zh",
      "script": "Hans",
      "region": "cn",
      "form": "official",
      "source": "wikidata",
      "verified": false
    },
    {
      "text": "洛克人ZX",
      "lang": "zh",
      "script": "Hant",
      "region": "tw",
      "form": "official",
      "source": "wikidata",
      "verified": false
    },
    {
      "text": "Mega Man ZX",
      "lang": "es",
      "script": "Latn",
      "region": "es",
      "form": "official",
      "source": "wikidata",
      "verified": false
    },
    {
      "text": "Mega Man ZX",
      "lang": "fr",
      "script": "Latn",
      "region": "fr",
      "form": "official",
      "source": "wikidata",
      "verified": false
    },
    {
      "text": "Mega Man ZX",
      "lang": "it",
      "script": "Latn",
      "region": "it",
      "form": "official",
      "source": "wikidata",
      "verified": false
    }
  ],
  "first_release_date": "2006-07-06",
  "external_ids": {
    "wikidata": "Q2319030",
    "mobygames": 24204
  }
}
