{
  "id": "rudolph-the-red-nosed-reindeer",
  "platform": "nds",
  "category": "main_game",
  "titles": [
    {
      "text": "Rudolph the Red-Nosed Reindeer",
      "lang": "en",
      "script": "Latn",
      "region": "us",
      "form": "official",
      "source": "wikidata",
      "verified": false
    }
  ],
  "first_release_date": "2010-11-09",
  "external_ids": {
    "wikidata": "Q7377481",
    "mobygames": 70033,
    "igdb": 228305
  },
  "roms": [
    {
      "name": "Rudolph - The Red-Nosed Reindeer (USA)",
      "source": "no_intro",
      "region": "us",
      "serial": "BRUE",
      "size": 16777216,
      "crc32": "3875cd6b",
      "md5": "0c182757262b9606e4cf44fefb7b9f13",
      "sha1": "dfaf72122e3c66b774f87bca2a05da1260de0b0c"
    }
  ],
  "media": [
    {
      "kind": "boxart",
      "url": "https://raw.githubusercontent.com/libretro-thumbnails/Nintendo_-_Nintendo_DS/master/Named_Boxarts/Rudolph%20-%20The%20Red-Nosed%20Reindeer%20%28USA%29.png",
      "source": "libretro_thumbnails",
      "region": "us"
    },
    {
      "kind": "screenshot",
      "url": "https://raw.githubusercontent.com/libretro-thumbnails/Nintendo_-_Nintendo_DS/master/Named_Snaps/Rudolph%20-%20The%20Red-Nosed%20Reindeer%20%28USA%29.png",
      "source": "libretro_thumbnails",
      "region": "us"
    }
  ],
  "descriptions": [
    {
      "text": "Join in all the Reindeer Games in this adaptation of the classic claymation holiday story.",
      "lang": "en",
      "source": "igdb"
    },
    {
      "text": "Computerspiel aus dem Jahr 2010",
      "lang": "de",
      "source": "wikidata"
    },
    {
      "text": "2010 video game",
      "lang": "en",
      "source": "wikidata"
    },
    {
      "text": "videojuego de 2010",
      "lang": "es",
      "source": "wikidata"
    },
    {
      "text": "jeu vidéo de 2010",
      "lang": "fr",
      "source": "wikidata"
    },
    {
      "text": "videogioco del 2010",
      "lang": "it",
      "source": "wikidata"
    },
    {
      "text": "компьютерная игра 2010 года",
      "lang": "ru",
      "source": "wikidata"
    },
    {
      "text": "videojogo de 2010",
      "lang": "pt",
      "source": "wikidata"
    }
  ]
}
