{
  "id": "sherlock-holmes-the-mystery-of-the-mummy",
  "platform": "nds",
  "category": "main_game",
  "titles": [
    {
      "text": "Sherlock Holmes: The Mystery of the Mummy",
      "lang": "en",
      "script": "Latn",
      "region": "us",
      "form": "official",
      "source": "wikidata",
      "verified": false
    },
    {
      "text": "셜록 홈즈: 미라의 미스터리",
      "lang": "ko",
      "script": "Hang",
      "region": "kr",
      "form": "official",
      "source": "wikidata",
      "verified": false
    },
    {
      "text": "Sherlock Holmes: el misterio de la momia",
      "lang": "es",
      "script": "Latn",
      "region": "es",
      "form": "official",
      "source": "wikidata",
      "verified": false
    },
    {
      "text": "Sherlock Holmes : Le Mystère de la momie",
      "lang": "fr",
      "script": "Latn",
      "region": "fr",
      "form": "official",
      "source": "wikidata",
      "verified": false
    },
    {
      "text": "Sherlock Holmes: Das Geheimnis der Mumie",
      "lang": "de",
      "script": "Latn",
      "region": "de",
      "form": "official",
      "source": "wikidata",
      "verified": false
    },
    {
      "text": "Sherlock Holmes - Il mistero della mummia",
      "lang": "it",
      "script": "Latn",
      "region": "it",
      "form": "official",
      "source": "wikidata",
      "verified": false
    }
  ],
  "first_release_date": "2002-01-01",
  "external_ids": {
    "wikidata": "Q1374448",
    "mobygames": 7910
  }
}
