{
  "id": "konami-gb-collection-vol-1",
  "platform": "gb",
  "category": "main_game",
  "titles": [
    {
      "text": "Konami GB Collection Vol.1",
      "lang": "en",
      "script": "Latn",
      "form": "official",
      "source": "no_intro",
      "verified": false,
      "region": "jp"
    },
    {
      "text": "コナミGBコレクション Vol.1",
      "lang": "ja",
      "script": "Kana",
      "region": "jp",
      "form": "official",
      "source": "romu",
      "verified": true
    },
    {
      "text": "コナミGBコレクションVol.1",
      "lang": "ja",
      "script": "Kana",
      "region": "jp",
      "form": "official",
      "source": "skyscraper_ja",
      "verified": true
    },
    {
      "text": "コナミGBコレクション",
      "lang": "ja",
      "script": "Kana",
      "region": "jp",
      "form": "official",
      "source": "gamelist_ja",
      "verified": true
    },
    {
      "text": "コナミ GB コレクション Vol.1",
      "lang": "ja",
      "script": "Kana",
      "region": "jp",
      "form": "official",
      "source": "igdb",
      "verified": true
    }
  ],
  "roms": [
    {
      "name": "Konami GB Collection Vol.1 (Japan) (SGB Enhanced)",
      "source": "no_intro",
      "region": "jp",
      "size": 524288,
      "crc32": "992cd78f",
      "md5": "74ec77e1cfbdc05bba5381b3f78d5dd9",
      "sha1": "dfb86b1b2db29a7086d60dc143374ef27b130580",
      "sha256": "7c4edefe1c662016e9b398c29164ac6c8bec013c9ce20dc860f39c49f58b9add"
    }
  ],
  "external_ids": {
    "igdb": 49835
  },
  "descriptions": [
    {
      "text": "このコンピレーションには、1つのカートリッジに4つのコナミタイトルが収められています：\nキャッスルヴァニア：ザ・アドベンチャー\nグラディウス（タイトル変更されたネメシス）\nコナミレーシング\nプロボテクター\n\n各ゲームはゲームボーイカラーとゲームボーイに完全対応しています。",
      "lang": "ja",
      "source": "romu"
    },
    {
      "text": "The Konami GB Collection is a series of video game compilations for the Game Boy Color. The compilations were originally released from 1997 to 1998 in Japan for Game Boy, and were later released in Europe in 2000 for Game Boy Color.\n\nIncluded in Volume 1:\n- Gradius (Nemesis)\n- Castlevania: The Adventure\n- Konami Racing (World Circuit Series)\n- Probotector (Operation C)\n\nDespite using the localized title Probotector, which was used for multiple Contra games in Europe, it does not feature robot characters as were used in those localizations.",
      "lang": "en",
      "source": "igdb"
    },
    {
      "text": "Konami GB Collection is a series of four video game compilations published by Konami, each comprising four of their previously released Game Boy titles on a single cartridge. The compilations were originally released from 1997 to 1998 in Japan on the Game Boy, and featured Super Game Boy palette and border support, with game descriptions and instructions provided by the girls from the original Tokimeki Memorial. The compilations later received a European release in 2000 for the Game Boy Color, which removed the Super Game Boy support and Tokimeki Memorial content but added colour support.",
      "lang": "en",
      "source": "wikipedia_en"
    }
  ],
  "first_release_date": "1997-09-25",
  "media": [
    {
      "kind": "boxart",
      "url": "https://raw.githubusercontent.com/libretro-thumbnails/Nintendo_-_Game_Boy/master/Named_Boxarts/Konami%20GB%20Collection%20Vol.1%20%28Japan%29%20%28SGB%20Enhanced%29.png",
      "source": "libretro_thumbnails",
      "region": "jp"
    },
    {
      "kind": "titlescreen",
      "url": "https://raw.githubusercontent.com/libretro-thumbnails/Nintendo_-_Game_Boy/master/Named_Titles/Konami%20GB%20Collection%20Vol.1%20%28Japan%29%20%28SGB%20Enhanced%29.png",
      "source": "libretro_thumbnails",
      "region": "jp"
    },
    {
      "kind": "screenshot",
      "url": "https://raw.githubusercontent.com/libretro-thumbnails/Nintendo_-_Game_Boy/master/Named_Snaps/Konami%20GB%20Collection%20Vol.1%20%28Japan%29%20%28SGB%20Enhanced%29.png",
      "source": "libretro_thumbnails",
      "region": "jp"
    }
  ]
}
