{
  "id": "snakebird-gb",
  "platform": "gb",
  "category": "main_game",
  "titles": [
    {
      "text": "Snakebird GB",
      "lang": "en",
      "script": "Latn",
      "region": "us",
      "form": "official",
      "source": "igdb",
      "verified": false
    }
  ],
  "external_ids": {
    "igdb": 324694
  },
  "first_release_date": "2016-09-23",
  "descriptions": [
    {
      "text": "This is a Gameboy recreation / fangame of the amazing puzzle game Snakebird, containing 10 all new levels.",
      "lang": "en",
      "source": "igdb"
    },
    {
      "text": "Happy snakebirding!",
      "lang": "en",
      "source": "igdb_storyline"
    }
  ]
}
