{
  "id": "kouyasai-a-sherd-of-youthful-memories",
  "platform": "ps1",
  "category": "main_game",
  "titles": [
    {
      "text": "Kouyasai: A Sherd of Youthful Memories",
      "lang": "en",
      "script": "Latn",
      "region": "us",
      "form": "official",
      "source": "igdb",
      "verified": false
    },
    {
      "text": "後夜祭",
      "lang": "ja",
      "script": "Jpan",
      "region": "jp",
      "form": "official",
      "source": "igdb",
      "verified": false
    }
  ],
  "external_ids": {
    "igdb": 166320
  },
  "first_release_date": "1999-02-25",
  "descriptions": [
    {
      "text": "The protagonist sets up his school's festival with the help of his classmates. He's able to get closer to them, and will obtain eventually a love ending (if it's with a girl) or a friendship ending (if it's with a boy).",
      "lang": "en",
      "source": "igdb"
    }
  ]
}
