{
  "id": "simple-1500-series-vol-72-the-beach-volley",
  "platform": "ps1",
  "category": "main_game",
  "titles": [
    {
      "text": "Simple 1500 Series Vol. 72 - The Beach Volley",
      "lang": "en",
      "script": "Latn",
      "form": "official",
      "source": "no_intro",
      "verified": false,
      "region": "jp"
    },
    {
      "text": "Simple 1500 シリーズ Vol.72 The ビーチバレー",
      "lang": "ja",
      "script": "Kana",
      "region": "jp",
      "form": "official",
      "source": "igdb",
      "verified": true
    }
  ],
  "roms": [
    {
      "name": "Simple 1500 Series Vol. 72 - The Beach Volley (Japan)",
      "source": "no_intro",
      "region": "jp",
      "size": 55738624,
      "crc32": "88080d5a",
      "md5": "7cee7e398707cd6c1b47d7873750c926",
      "sha1": "45fc9d12e2eec101a06eebaa70bdfefed6159a6d"
    }
  ],
  "external_ids": {
    "igdb": 203068
  },
  "media": [
    {
      "kind": "boxart",
      "url": "https://raw.githubusercontent.com/libretro-thumbnails/Sony_-_PlayStation/master/Named_Boxarts/Simple%201500%20Series%20Vol.%2072%20-%20The%20Beach%20Volley%20%28Japan%29.png",
      "source": "libretro_thumbnails",
      "region": "jp"
    },
    {
      "kind": "titlescreen",
      "url": "https://raw.githubusercontent.com/libretro-thumbnails/Sony_-_PlayStation/master/Named_Titles/Simple%201500%20Series%20Vol.%2072%20-%20The%20Beach%20Volley%20%28Japan%29.png",
      "source": "libretro_thumbnails",
      "region": "jp"
    },
    {
      "kind": "screenshot",
      "url": "https://raw.githubusercontent.com/libretro-thumbnails/Sony_-_PlayStation/master/Named_Snaps/Simple%201500%20Series%20Vol.%2072%20-%20The%20Beach%20Volley%20%28Japan%29.png",
      "source": "libretro_thumbnails",
      "region": "jp"
    }
  ],
  "descriptions": [
    {
      "text": "A total of 26 characters from 8 countries appear in this game, which is fully-packed with combination play that is unique to beach volleyball. Different to volleyball, it is necessary to predict and calculate wind speed to determine whether you should attack or fake in. Realizing simple but in-depth controls, you can learn while you play in Training Mode.",
      "lang": "en",
      "source": "igdb"
    }
  ]
}
