{
  "id": "uno",
  "platform": "ps1",
  "category": "main_game",
  "titles": [
    {
      "text": "Uno",
      "lang": "en",
      "script": "Latn",
      "region": "us",
      "form": "official",
      "source": "igdb",
      "verified": false
    }
  ],
  "external_ids": {
    "igdb": 255867
  },
  "first_release_date": "1998-04-02",
  "descriptions": [
    {
      "text": "A Japanese game adaptation of the Mattel card game Uno, featuring a story mode set in a high school's Uno Club.",
      "lang": "en",
      "source": "igdb"
    },
    {
      "text": "The game includes a single-player story mode (known as \"Advanced UNO\") set in a private high school. Players control Shunichi Uno, a hot-blooded Uno player who seeks to defeat the other members of the school's Uno Club to participate in the National High School Uno Championship.",
      "lang": "en",
      "source": "igdb_storyline"
    }
  ]
}
