{
  "id": "world-cup-golf-professional-edition",
  "platform": "ps1",
  "category": "main_game",
  "titles": [
    {
      "text": "World Cup Golf: Professional Edition",
      "lang": "en",
      "script": "Latn",
      "region": "us",
      "form": "official",
      "source": "igdb",
      "verified": false
    }
  ],
  "external_ids": {
    "igdb": 4340
  },
  "first_release_date": "1994-12-31",
  "descriptions": [
    {
      "text": "Take on the best with WORLD CUP GOLF: Professional Edition. Get onto the green in the Practice mode, and work on any hole that gives you problems. In Normal mode, challenge the course alone or play against someone with 15 different game types such as skins and match play.\n\nTournament mode provides you with the ability to create your own event. No matter how you play the course, you'll have full control over your player's stance as well as the weather and the ground conditions. While you play, your auditory sense is treated to CD quality music and digitized speech. See how long you would last as an expert in WORLD CUP GOLF: Professional Edition.",
      "lang": "en",
      "source": "igdb"
    },
    {
      "text": "World Cup Golf: Hyatt Dorado Beach is a sports video game developed by Arc Developments and published by U.S. Gold. It is based on the 1994 event set at Dorado Beach in Puerto Rico. Conceived as the most technologically advanced and realistic golf simulation ever, the game was built using Silicon Graphics workstations exclusively for platforms supporting the CD-ROM format. It was initially released on MS-DOS, 3DO, and CD-i in 1994. Conversions were released as World Cup Golf: Professional Edition for PlayStation and Saturn in 1996. Versions for the Sega CD and CD32 were cancelled. The game received a mixed reaction from critics.",
      "lang": "en",
      "source": "wikipedia_en"
    }
  ]
}
